appwrite_annotations/__init__.py
appwrite_annotations/base.py
appwrite_annotations/boolean_attribute.py
appwrite_annotations/datetime_attribute.py
appwrite_annotations/email_attribute.py
appwrite_annotations/enum_attribute.py
appwrite_annotations/exceptions.py
appwrite_annotations/float_attribute.py
appwrite_annotations/integer_attribute.py
appwrite_annotations/ip_address_attribute.py
appwrite_annotations/relationship_attribute.py
appwrite_annotations/string_attribute.py
appwrite_annotations-0.5.0.dist-info/LICENSE
appwrite_annotations-0.5.0.dist-info/METADATA
appwrite_annotations-0.5.0.dist-info/WHEEL
appwrite_annotations-0.5.0.dist-info/top_level.txt
appwrite_annotations-0.5.0.dist-info/RECORD
