Metadata-Version: 2.1
Name: appwrite_annotations
Version: 0.5.0
Summary: A Python library for defining and annotating class attributes with custom metadata for appwrite.
Home-page: https://github.com/Zia-Ch/appwrite_annotations
Author: Zia Ur Rahman
Author-email: ziaurrahmanchoudhary@gmail.com
Classifier: Programming Language :: Python :: 3
Classifier: License :: OSI Approved :: MIT License
Classifier: Operating System :: OS Independent
Requires-Python: >=3.7
License-File: LICENSE
